{
  "document_id": "24652",
  "title": "NA-ULIP",
  "word_text": "https://www.bajajallianzlife.com/life-insurance-guide/life/importance-of-reading-fine-print-before-buying-an-insurance-policy.html\nImportance of Reading Fine Print Before Buying an Insurance Policy\nThere are two types of people: those who go through the life insurance policy terms and conditions section to learn more about what they might sign, and those who avoid doing so out of inconvenience. After all, reading the fine print of any document may be challenging as it involves breaking down a bit of legal jargon. Even though most people might not have the time or interest in reading this section of their insurance policy, there are circumstances where knowing this information comes in handy.\nHere’s why reading the fine print of your insurance policy is essential, and how doing this can save you the future hassle, and losing money.\nWhat is the fine print in an insurance policy?\nFirst, let’s describe what the fine print of a life insurance policy is. These are often labelled as the “terms and conditions of life insurance policy'' and contain information that tends to add nuance to what is stated on your life insurance policy document. This is what we are referring to with the term 'fine print.'\nThe second you sign your insurance papers and submit your documents for approval, the underlying assumption is that you have read the fine print and agree to the terms and conditions of life insurance policy.\nWhy is fine print important to read\nWith the above backdrop, what makes reading the fine print so important? Here are a few reasons you should make it a habit to browse the terms and conditions of any contract you plan on signing:\n● Gives you a better understanding of your policy:When you choose to go through the fine print of your life insurance policy, you’re ensuring that you are aware of, as well as understand all of the provisions of your policy. This practice makes you a smarter and more informed customer. In fact, you might find information about your policy in this section that is enough to either convince you or dissuade you from signing your life insurance policy documents. It's important to avoid taking the chance of assuming you know everything about a life insurance policy before you sign the papers.\n● Saves you money and time :If you were to buy a life insurance policy without going through its terms and conditions, and it so happens that the policy is not valid under certain circumstances which frequently occur for you, then paying premiums towards it becomes futile. Reading the fine print can save you from spending copious amounts of money on a policy that is unsuitable for you.\n● Offers you legal protection:Every document's terms and conditions are designed to help both parties legally. When you go through the terms and conditions of your policy, you know exactly what to expect from the policy. If you do not receive, for whatever reason, what is written in the signed agreement, you are within your rights to let your insurer know. Remember that if you do not fully agree with the life insurance terms and conditions, nobody can force you to sign the insurance contract. Hence, reading the fine print can help you learn what is expected from your policy, and demand it if you are not getting what was promised.\nConclusion\nAt the end of the day, you do not want your insurance claim to get rejected for a reason that comes as a surprise to you. Instead, you want a policy whose protection is guaranteed in the agreed-upon circumstances. For this, it is necessary to read the terms and conditions of your policy and understand exactly what you plan on signing. You can save yourself future hassle time, and money by reading this section of your policy, and also become a more informed customer in future insurance purchases.\n##Our policy covers COVID 19 claims subject to policy terms and conditions being met\n3Discount is available for regular premium and limited premium payment frequency under all variants of this product.\n2Above illustration is considering Male aged 25 years | Non-Smoker | Life Cover Variant | Policy term (PT)– 30 years | Premium Payment Term (PPT) – 30 years | Sum Assured opted is Rs. 1,00,00,000 | Online Channel | medical rates | Annual Premium Payment Mode | Premium shown above is exclusive of Goods &amp; Service Tax/any other applicable tax levied, subject to changes in tax laws, and any extra premium and is for illustrative purpose only.\nIn this policy, the investment risk in investment portfolio is borne by the policyholder. Investment in ULIPs is subject to risks associated with the capital markets. The policy holder is solely responsible for his/her decisions while investing in ULIPs.\n~Tax benefits as per prevailing Income tax laws shall apply. Please check with your tax consultant for eligibility.\nThe above information is for general understanding and is meant to educate the general public at large. The reader will have to verify the facts, law and content with the prevailing tax statutes and seek appropriate professional advice before acting on the basis of the above information.\nThe views stated in this article is not to be construed as investment advice and readers are suggested to seek independent financial advice before making any investment decisions. For more details on risk factors, terms and conditions please read sales brochure &amp; policy document (available on www.bajajlifeinsurance.com) carefully before concluding a sale.",
  "full_pdf_text": "",
  "word_comments": [],
  "changes": [],
  "has_changes": false
}