{
  "document_id": "5123",
  "title": "NA-Non ULIP",
  "word_text": "The 50-30-20 Rule\nThis is an efficient rule that works on the basis of dividing your income to meet your expenses in an organized manner. In a perfect world, if you can manage it, you should stick to the following division of your total in-hand income:\nFor Need-based Expenses (groceries, EMI, rent, etc.) - 50%\nFor Wants-based Expenses (holidays, entertainment, shopping sprees,etc.) - 30%\nFor Savings (mutual funds, equity, FDs, debt, etc.) - 20%\nSay you earn a salary, in-hand, of Rs. 2 lakh. Your need-based expenses will amount to Rs. 1 lakh straight away. The rest can be divided into desire-based expenses and savings. However, you should never compromise on the savings part. The least you should aim to save out of your earnings is 20%. If you save more, then that’s a bonus. Furthermore, as your income increases, your requirements may not increase in the same proportion. Hence, you may have surplus funds that you can invest. For instance, when you are young, you may have rental expenses, but once you buy a house when you are older (assuming your loan is paid up), your rental expenses are non-existent.",
  "full_pdf_text": "",
  "word_comments": [],
  "changes": [],
  "has_changes": false
}